durationdetective/__init__.py
durationdetective/__main__.py
durationdetective/cli.py
durationdetective/durationdetective.py
duration_detective-1.0.0.dist-info/LICENSE
duration_detective-1.0.0.dist-info/METADATA
duration_detective-1.0.0.dist-info/WHEEL
duration_detective-1.0.0.dist-info/entry_points.txt
duration_detective-1.0.0.dist-info/top_level.txt
duration_detective-1.0.0.dist-info/RECORD
