Metadata-Version: 2.1
Name: duration-detective
Version: 1.0.0
Summary: A Tree like tool to generate directory tree diagrams for media files in folders and Subfolders
Home-page: https://github.com/3l-d1abl0/DurationDetective
Author: Sameer Barha
Author-email: sameer.barha12@gmail.com
Maintainer: Sameer Barha
Maintainer-email: sameer.barha12@gmail.com
License: MIT
Classifier: License :: OSI Approved :: MIT License
Classifier: Programming Language :: Python :: 3
Classifier: Programming Language :: Python :: 3.10
License-File: LICENSE
Requires-Dist: emoji ==2.8.0
Requires-Dist: ffmpeg-python ==0.2.0
